clipunch/__init__.py
clipunch/cli.py
clipunch-1.0.0.dist-info/LICENSE
clipunch-1.0.0.dist-info/METADATA
clipunch-1.0.0.dist-info/WHEEL
clipunch-1.0.0.dist-info/entry_points.txt
clipunch-1.0.0.dist-info/RECORD
