Metadata-Version: 2.1
Name: clipunch
Version: 1.0.0
Summary: A CLI tool to create punchard visualizations.
License: AGPL-3.0-only
Author: HelgeCPH
Author-email: ropf@itu.dk
Requires-Python: >=3.10,<4.0
Classifier: License :: OSI Approved :: GNU Affero General Public License v3
Classifier: Programming Language :: Python :: 3
Classifier: Programming Language :: Python :: 3.10
Classifier: Programming Language :: Python :: 3.11
Requires-Dist: jinja2 (>=3.1.4,<4.0.0)
Requires-Dist: python-dateutil (>=2.9.0.post0,<3.0.0)
Requires-Dist: sty (>=1.0.6,<2.0.0)
